alan/__init__.py
alan/__main__.py
alan/interface.py
alan/machine.py
alan-0.4.1.dist-info/LICENSE
alan-0.4.1.dist-info/METADATA
alan-0.4.1.dist-info/WHEEL
alan-0.4.1.dist-info/entry_points.txt
alan-0.4.1.dist-info/top_level.txt
alan-0.4.1.dist-info/RECORD
