Metadata-Version: 2.1
Name: alan
Version: 0.4.1
Summary: A programming language for designing Turing machines
Home-page: https://github.com/kelvindecosta/alan
Author: Kelvin DeCosta
Author-email: decostakelvin@gmail.com
License: MIT
Platform: UNKNOWN
Classifier: Programming Language :: Python :: 3
Classifier: License :: OSI Approved :: MIT License
Classifier: Operating System :: OS Independent
Requires-Python: >=3.6
Requires-Dist: imageio
Requires-Dist: pydot
